atldld/__init__.py
atldld/__main__.py
atldld/base.py
atldld/config.py
atldld/constants.py
atldld/dataset.py
atldld/plot.py
atldld/requests.py
atldld/sync.py
atldld/utils.py
atldld/version.py
atldld/cli/__init__.py
atldld/cli/dataset.py
atldld/cli/download.py
atldld/cli/info.py
atldld/cli/root.py
atldld/cli/search.py
atldld-0.3.4.dist-info/AUTHORS.md
atldld-0.3.4.dist-info/LICENSE.txt
atldld-0.3.4.dist-info/METADATA
atldld-0.3.4.dist-info/WHEEL
atldld-0.3.4.dist-info/entry_points.txt
atldld-0.3.4.dist-info/top_level.txt
atldld-0.3.4.dist-info/RECORD
