Metadata-Version: 2.1
Name: atldld
Version: 0.3.4
Summary: Search, download, and prepare atlas data.
Home-page: https://github.com/BlueBrain/Atlas-Download-Tools
Author: Blue Brain Project, EPFL
License: LGPLv3
Classifier: License :: OSI Approved :: GNU Lesser General Public License v3 (LGPLv3)
Classifier: Operating System :: Unix
Classifier: Operating System :: MacOS
Classifier: Programming Language :: Python
Classifier: Programming Language :: Python :: 3
Classifier: Programming Language :: Python :: 3.6
Classifier: Programming Language :: Python :: 3.7
Classifier: Programming Language :: Python :: 3.8
Classifier: Programming Language :: Python :: 3.9
Classifier: Programming Language :: Python :: 3 :: Only
Requires-Python: >=3.6
License-File: LICENSE.txt
License-File: AUTHORS.md
Requires-Dist: Pillow
Requires-Dist: appdirs
Requires-Dist: click (>=8)
Requires-Dist: matplotlib
Requires-Dist: numpy
Requires-Dist: requests
Requires-Dist: scikit-image
Requires-Dist: opencv-python
Requires-Dist: dataclasses ; python_version < "3.7"
Provides-Extra: dev
Requires-Dist: bandit ; extra == 'dev'
Requires-Dist: black ; extra == 'dev'
Requires-Dist: flake8 ; extra == 'dev'
Requires-Dist: isort ; extra == 'dev'
Requires-Dist: mypy ; extra == 'dev'
Requires-Dist: pydocstyle ; extra == 'dev'
Requires-Dist: pytest ; extra == 'dev'
Requires-Dist: pytest-cov ; extra == 'dev'
Requires-Dist: pytest-mock ; extra == 'dev'
Requires-Dist: responses ; extra == 'dev'
Requires-Dist: tox ; extra == 'dev'
Provides-Extra: docs
Requires-Dist: sphinx (>=1.3) ; extra == 'docs'
Requires-Dist: sphinx-bluebrain-theme ; extra == 'docs'
